z3c/breadcrumb/README.rst
z3c/breadcrumb/__init__.py
z3c/breadcrumb/browser.py
z3c/breadcrumb/configure.zcml
z3c/breadcrumb/interfaces.py
z3c/breadcrumb/tests.py
z3c_breadcrumb-4.0.dist-info/LICENSE.txt
z3c_breadcrumb-4.0.dist-info/METADATA
z3c_breadcrumb-4.0.dist-info/WHEEL
z3c_breadcrumb-4.0.dist-info/top_level.txt
z3c_breadcrumb-4.0.dist-info/RECORD
